{"stats":{"minecraft:dropped":{"examplemod:cranberry":120},"minecraft:picked_up":{"examplemod:elderberry":60,"examplemod:cranberry":123,"minecraft:sugar_cane":3},"minecraft:used":{"examplemod:elderberry_bush":2,"examplemod:cranberry_bush":5,"examplemod:elderberry":24,"examplemod:angelica":2,"examplemod:angelica_root":1,"examplemod:cranberry":3},"minecraft:custom":{"minecraft:jump":51,"minecraft:time_since_rest":36873,"minecraft:play_one_minute":36873,"minecraft:crouch_one_cm":2277,"minecraft:leave_game":12,"minecraft:sprint_one_cm":3748,"minecraft:time_since_death":36873,"minecraft:walk_on_water_one_cm":145,"minecraft:walk_one_cm":24150,"minecraft:sneak_time":671,"minecraft:talked_to_villager":5,"minecraft:drop":2,"minecraft:fly_one_cm":339634,"minecraft:open_chest":1}},"DataVersion":2586}